telegram_plugin_gamesdk/telegram_plugin.py
telegram_plugin_gamesdk-0.1.0.dist-info/METADATA
telegram_plugin_gamesdk-0.1.0.dist-info/WHEEL
telegram_plugin_gamesdk-0.1.0.dist-info/RECORD
