Metadata-Version: 2.3
Name: telegram-plugin-gamesdk
Version: 0.1.0
Summary: Telegram Plugin for Python SDK for GAME by Virtuals
Author: Ang Weoy Yang
Author-email: weoyyang00@gmail.com
Requires-Python: >=3.9
Classifier: Programming Language :: Python :: 3
Classifier: Programming Language :: Python :: 3.9
Classifier: Programming Language :: Python :: 3.10
Classifier: Programming Language :: Python :: 3.11
Classifier: Programming Language :: Python :: 3.12
Classifier: Programming Language :: Python :: 3.13
Requires-Dist: python-telegram-bot (>=21.11.1)
